tilt_ble/__init__.py
tilt_ble/parser.py
tilt_ble/py.typed
tilt_ble-1.0.1.dist-info/METADATA
tilt_ble-1.0.1.dist-info/WHEEL
tilt_ble-1.0.1.dist-info/licenses/LICENSE
tilt_ble-1.0.1.dist-info/RECORD
